nba_mcp_server/__init__.py
nba_mcp_server/__main__.py
nba_mcp_server/server.py
nba_stats_mcp-0.1.6.dist-info/METADATA
nba_stats_mcp-0.1.6.dist-info/WHEEL
nba_stats_mcp-0.1.6.dist-info/entry_points.txt
nba_stats_mcp-0.1.6.dist-info/licenses/LICENSE
nba_stats_mcp-0.1.6.dist-info/RECORD
