Metadata-Version: 2.4
Name: nba-stats-mcp
Version: 0.1.6
Summary: MCP server for accessing NBA statistics and data via direct API calls
Project-URL: Homepage, https://github.com/labeveryday/nba_mcp_server
Project-URL: Repository, https://github.com/labeveryday/nba_mcp_server
Project-URL: Issues, https://github.com/labeveryday/nba_mcp_server/issues
Project-URL: Documentation, https://github.com/labeveryday/nba_mcp_server#readme
Author-email: Du'An Lightfoot <labeveryday@users.noreply.github.com>
License: MIT
License-File: LICENSE
Keywords: api,basketball,mcp,model-context-protocol,nba,sports,stats
Classifier: Development Status :: 4 - Beta
Classifier: Intended Audience :: Developers
Classifier: License :: OSI Approved :: MIT License
Classifier: Operating System :: OS Independent
Classifier: Programming Language :: Python :: 3
Classifier: Programming Language :: Python :: 3.10
Classifier: Programming Language :: Python :: 3.11
Classifier: Programming Language :: Python :: 3.12
Classifier: Topic :: Games/Entertainment
Classifier: Topic :: Software Development :: Libraries :: Python Modules
Requires-Python: >=3.10
Requires-Dist: httpx>=0.27.0
Requires-Dist: mcp>=1.0.0
Provides-Extra: dev
Requires-Dist: bandit>=1.7.9; extra == 'dev'
Requires-Dist: build>=1.2.2.post1; extra == 'dev'
Requires-Dist: pytest-asyncio>=0.21.0; extra == 'dev'
Requires-Dist: pytest-cov>=4.0; extra == 'dev'
Requires-Dist: pytest-mock>=3.10; extra == 'dev'
Requires-Dist: pytest>=7.0; extra == 'dev'
Requires-Dist: ruff>=0.8.0; extra == 'dev'
Requires-Dist: twine>=5.1.1; extra == 'dev'
